huaweicloudsdkdrs/__init__.py
huaweicloudsdkdrs/v3/__init__.py
huaweicloudsdkdrs/v3/drs_async_client.py
huaweicloudsdkdrs/v3/drs_client.py
huaweicloudsdkdrs/v3/model/__init__.py
huaweicloudsdkdrs/v3/model/add_data_transformation_req.py
huaweicloudsdkdrs/v3/model/alarm_notify_info.py
huaweicloudsdkdrs/v3/model/api_http_null_resp.py
huaweicloudsdkdrs/v3/model/az_info_resp.py
huaweicloudsdkdrs/v3/model/batch_change_data_request.py
huaweicloudsdkdrs/v3/model/batch_change_data_response.py
huaweicloudsdkdrs/v3/model/batch_check_jobs_request.py
huaweicloudsdkdrs/v3/model/batch_check_jobs_response.py
huaweicloudsdkdrs/v3/model/batch_check_results_request.py
huaweicloudsdkdrs/v3/model/batch_check_results_response.py
huaweicloudsdkdrs/v3/model/batch_create_job_req.py
huaweicloudsdkdrs/v3/model/batch_create_jobs_request.py
huaweicloudsdkdrs/v3/model/batch_create_jobs_response.py
huaweicloudsdkdrs/v3/model/batch_data_transformation_req.py
huaweicloudsdkdrs/v3/model/batch_delete_job_req.py
huaweicloudsdkdrs/v3/model/batch_delete_jobs_request.py
huaweicloudsdkdrs/v3/model/batch_delete_jobs_response.py
huaweicloudsdkdrs/v3/model/batch_import_smn_info_req.py
huaweicloudsdkdrs/v3/model/batch_job_action_req.py
huaweicloudsdkdrs/v3/model/batch_limit_speed_req.py
huaweicloudsdkdrs/v3/model/batch_list_job_details_request.py
huaweicloudsdkdrs/v3/model/batch_list_job_details_response.py
huaweicloudsdkdrs/v3/model/batch_list_job_status_request.py
huaweicloudsdkdrs/v3/model/batch_list_job_status_response.py
huaweicloudsdkdrs/v3/model/batch_list_progresses_request.py
huaweicloudsdkdrs/v3/model/batch_list_progresses_response.py
huaweicloudsdkdrs/v3/model/batch_list_rpos_and_rtos_request.py
huaweicloudsdkdrs/v3/model/batch_list_rpos_and_rtos_response.py
huaweicloudsdkdrs/v3/model/batch_list_struct_detail_request.py
huaweicloudsdkdrs/v3/model/batch_list_struct_detail_response.py
huaweicloudsdkdrs/v3/model/batch_list_struct_process_request.py
huaweicloudsdkdrs-3.1.184.dist-info/METADATA
huaweicloudsdkdrs-3.1.184.dist-info/WHEEL
huaweicloudsdkdrs-3.1.184.dist-info/licenses/LICENSE
huaweicloudsdkdrs-3.1.184.dist-info/RECORD
